rgbterminal/__init__.py
rgbterminal/core.py
rgbterminal-0.3.0.dist-info/licenses/LICENSE
rgbterminal-0.3.0.dist-info/METADATA
rgbterminal-0.3.0.dist-info/WHEEL
rgbterminal-0.3.0.dist-info/top_level.txt
rgbterminal-0.3.0.dist-info/RECORD
